{
  "main": {
    "id": "a36468cf42ef202a",
    "type": "split",
    "children": [
      {
        "id": "464f892558ffd6ba",
        "type": "tabs",
        "children": [
          {
            "id": "8132aef68b7eb22b",
            "type": "leaf",
            "state": {
              "type": "empty",
              "state": {},
              "icon": "lucide-file",
              "title": "New tab"
            }
          }
        ]
      }
    ],
    "direction": "vertical"
  },
  "left": {
    "id": "d51e40ee6c39347d",
    "type": "split",
    "children": [
      {
        "id": "2c1d95e1264e82a1",
        "type": "tabs",
        "children": [
          {
            "id": "e1025940bba3c3ee",
            "type": "leaf",
            "state": {
              "type": "file-explorer",
              "state": {
                "sortOrder": "alphabetical"
              },
              "icon": "lucide-folder-closed",
              "title": "Files"
            }
          },
          {
            "id": "2a66c58aea4dee85",
            "type": "leaf",
            "state": {
              "type": "search",
              "state": {
                "query": "tag:#include와",
                "matchingCase": false,
                "explainSearch": false,
                "collapseAll": false,
                "extraContext": false,
                "sortOrder": "alphabetical"
              },
              "icon": "lucide-search",
              "title": "Search"
            }
          },
          {
            "id": "34ef649c1a5be4b6",
            "type": "leaf",
            "state": {
              "type": "bookmarks",
              "state": {},
              "icon": "lucide-bookmark",
              "title": "Bookmarks"
            }
          }
        ]
      }
    ],
    "direction": "horizontal",
    "width": 249.5
  },
  "right": {
    "id": "b314ce004c003f26",
    "type": "split",
    "children": [
      {
        "id": "aab0280c6bac5fd3",
        "type": "tabs",
        "children": [
          {
            "id": "19b0e6f22b730d78",
            "type": "leaf",
            "state": {
              "type": "backlink",
              "state": {
                "file": "iOS/Lazy Sequence.md",
                "collapseAll": false,
                "extraContext": false,
                "sortOrder": "alphabetical",
                "showSearch": false,
                "searchQuery": "",
                "backlinkCollapsed": false,
                "unlinkedCollapsed": true
              },
              "icon": "links-coming-in",
              "title": "Backlinks for Lazy Sequence"
            }
          },
          {
            "id": "964793cd979be8e5",
            "type": "leaf",
            "state": {
              "type": "outgoing-link",
              "state": {
                "file": "src/index.md",
                "linksCollapsed": false,
                "unlinkedCollapsed": true
              },
              "icon": "links-going-out",
              "title": "Outgoing links from index"
            }
          },
          {
            "id": "7c169f09a8514bac",
            "type": "leaf",
            "state": {
              "type": "tag",
              "state": {
                "sortOrder": "frequency",
                "useHierarchy": true
              },
              "icon": "lucide-tags",
              "title": "Tags"
            }
          },
          {
            "id": "92d9ed53ad8d07f9",
            "type": "leaf",
            "state": {
              "type": "outline",
              "state": {
                "file": "src/index.md"
              },
              "icon": "lucide-list",
              "title": "Outline of index"
            }
          },
          {
            "id": "b332b462d7d786c4",
            "type": "leaf",
            "state": {
              "type": "git-view",
              "state": {},
              "icon": "git-pull-request",
              "title": "Source Control"
            }
          }
        ],
        "currentTab": 4
      }
    ],
    "direction": "horizontal",
    "width": 300,
    "collapsed": true
  },
  "left-ribbon": {
    "hiddenItems": {
      "switcher:Open quick switcher": false,
      "graph:Open graph view": false,
      "canvas:Create new canvas": false,
      "daily-notes:Open today's daily note": false,
      "templates:Insert template": false,
      "command-palette:Open command palette": false,
      "obsidian-git:Open Git source control": false,
      "obsidian42-brat:BRAT": false,
      "webpage-html-export:Export as HTML": false
    }
  },
  "active": "e1025940bba3c3ee",
  "lastOpenFiles": [
    "Untitled.canvas",
    "Golf Simulator/Golf Simulator using SFML.md",
    "Algorithm/LeetCode/198. House Robber.md",
    "Algorithm/LeetCode/217. Contains Duplicate.md",
    "Algorithm/LeetCode/78. Subsets.md",
    "Algorithm/LeetCode/70. Climbing Stair.md",
    "Algorithm/LeetCode/62. Unique Paths.md",
    "2025-01-07.md",
    "iOS/Missing required module 'RxCocoaRuntime'에 대한 고찰 - SPM과 UnitTest에서의 오류.md",
    "Algorithm/LeetCode",
    "Hose/Develop.md",
    "Hose/내가 블로그를 시작한 이유.md",
    "docs/site-lib/search-index.json",
    "docs/site-lib/metadata.json",
    "docs/images/robot_maze.png",
    "CPP/Problem1.md",
    "CPP/포인터에 const 사용하기.md",
    "CPP/참조 vs 포인터.md",
    "UE/Build System.md",
    "UE/아틀라스.md",
    "UE/Unreal Engine만의 기본 타입이 있는 이유와 문자열.md",
    "UE/PhysX iOS 빌드.md",
    "UE/Navigation System.md",
    "UE/Slate Widget Examples.md",
    "UE/Slate Overview.md",
    "UE/Slate Architecture.md",
    "iOS/Swift, Objective - C interoperability.md",
    "iOS/Objective - C.md",
    "iOS/Network Timeout UnitTest.md",
    "iOS/Orientation.md",
    "docs/algorithm/blind75/217.-contains-duplicate.html",
    "docs/algorithm/blind75/78.-subsets.html",
    "Hose/Resume/Resume.canvas",
    "docs/algorithm/blind75/70.-climbing-stair.html",
    "docs/images/robot_maze.html",
    "docs/algorithm/blind75/62.-unique-paths.html",
    "docs/algorithm/blind75",
    "images/robot_maze.png",
    "attachments",
    "docs/site-lib/media/favicon.png",
    "docs/site-lib/media/874d8b8e340f75575caa.svg",
    "docs/images/whoami.png",
    "docs/images/wbp_ui_transition.png",
    "docs/images/vertext_shader_parallel.png",
    "docs/images/vertex_shader.png",
    "docs/images/var_error.jpg",
    "docs/images/using_uniform.png"
  ]
}